codestamper/__init__.py
codestamper/codestamper.py
codestamper/gitutils.py
codestamper/pythonenv.py
codestamper-0.3.2.dist-info/LICENSE
codestamper-0.3.2.dist-info/METADATA
codestamper-0.3.2.dist-info/WHEEL
codestamper-0.3.2.dist-info/top_level.txt
codestamper-0.3.2.dist-info/RECORD
