Metadata-Version: 2.1
Name: codestamper
Version: 0.3.2
Summary: Ensure code traceability in ML experiments
Home-page: https://github.com/bmsan/codestamper
Author: Bogdan Sandoi
Author-email: bogdan.sandoi@gmail.com
Classifier: Programming Language :: Python :: 3
Classifier: License :: OSI Approved :: MIT License
Classifier: Operating System :: OS Independent
Requires-Python: >=3.7
License-File: LICENSE
Requires-Dist: PyYAML (>=5.0)
